{"cameraMode":{"drawMode":0,"name":"Shaded","section":"Shading Mode"},"sceneLighting":true,"audioPlay":false,"sceneViewState":{"m_AlwaysRefresh":false,"showFog":true,"showSkybox":true,"showFlares":true,"showImageEffects":true,"showParticleSystems":true,"showVisualEffectGraphs":true,"m_FxEnabled":false},"in2DMode":false,"pivot":{"x":63.61685562133789,"y":-43.2087516784668,"z":21.028825759887697},"rotation":{"x":0.17777886986732484,"y":0.7712795734405518,"z":-0.24431459605693818,"w":0.5604647397994995},"size":51.132625579833987,"orthographic":false}