{"cameraMode":{"drawMode":0,"name":"Shaded","section":"Shading Mode"},"sceneLighting":true,"audioPlay":false,"sceneViewState":{"m_AlwaysRefresh":false,"showFog":true,"showSkybox":true,"showFlares":true,"showImageEffects":true,"showParticleSystems":true,"showVisualEffectGraphs":true,"m_FxEnabled":false},"in2DMode":false,"pivot":{"x":159.80381774902345,"y":-165.48793029785157,"z":-96.58460998535156},"rotation":{"x":0.1764213740825653,"y":0.809208333492279,"z":-0.30171331763267519,"w":0.4725196361541748},"size":134.27235412597657,"orthographic":false}